taxadb2/__init__.py
taxadb2/__main__.py
taxadb2/accessionid.py
taxadb2/app.py
taxadb2/download.py
taxadb2/names.py
taxadb2/parser.py
taxadb2/schema.py
taxadb2/taxadb.py
taxadb2/taxid.py
taxadb2/util.py
taxadb2/version.py
taxadb2/test/conftest.py
taxadb2/test/test_taxadb.py
taxadb2-0.12.3.dist-info/LICENSE
taxadb2-0.12.3.dist-info/METADATA
taxadb2-0.12.3.dist-info/WHEEL
taxadb2-0.12.3.dist-info/entry_points.txt
taxadb2-0.12.3.dist-info/top_level.txt
taxadb2-0.12.3.dist-info/RECORD
