Metadata-Version: 2.2
Name: taxadb2
Version: 0.12.3
Summary: Locally query the NCBI taxonomy
Author-email: Kristian K Ullrich <ullrich@evolbio.mpg.de>, Hadrien Gourlé <hadrien.gourle@slu.se>, Juliette Hayer <juliette.hayer@slu.se>, Emmanuel Quevillon <tuco@pasteur.fr>
Maintainer-email: Kristian K Ullrich <ullrich@evolbio.mpg.de>
License: MIT
Project-URL: Homepage, https://github.com/kullrich/taxadb2
Project-URL: Bug Tracker, https://github.com/kullrich/taxadb2/issues
Project-URL: documentation, https://taxadb2.readthedocs.io/en/latest/
Project-URL: repository, https://github.com/kullrich/taxadb2
Keywords: ncbi,taxonomy
Classifier: Development Status :: 3 - Alpha
Classifier: License :: OSI Approved :: MIT License
Classifier: Topic :: Scientific/Engineering :: Bio-Informatics
Classifier: Programming Language :: Python :: 3.10
Classifier: Programming Language :: Python :: 3.11
Classifier: Programming Language :: Python :: 3.12
Classifier: Intended Audience :: Science/Research
Classifier: Intended Audience :: Education
Requires-Python: >=3.10
License-File: LICENSE
Requires-Dist: requests
Requires-Dist: peewee>=3.8.2
Requires-Dist: tqdm
Provides-Extra: test
Requires-Dist: pytest; extra == "test"
Requires-Dist: configparser; extra == "test"
Provides-Extra: postgres
Requires-Dist: psycopg2>=2.6.2; extra == "postgres"
Provides-Extra: mysql
Requires-Dist: PyMySQL>=0.7.10; extra == "mysql"
